{
  "openapi": "3.0.1",
  "info": {
    "title": "WebApi, Version=1.0.0.0, Culture=neutral, PublicKeyToken=null",
    "version": "1.0"
  },
  "paths": {
    "/api/BlogPreviews": {
      "get": {
        "tags": [
          "BlogPreviews"
        ],
        "parameters": [
          {
            "name": "Limit",
            "in": "query",
            "schema": {
              "type": "integer",
              "format": "int32"
            }
          }
        ],
        "responses": {
          "200": {
            "description": "OK",
            "content": {
              "text/plain": {
                "schema": {
                  "type": "array",
                  "items": {
                    "$ref": "#/components/schemas/BlogPreviewDto"
                  }
                }
              },
              "application/json": {
                "schema": {
                  "type": "array",
                  "items": {
                    "$ref": "#/components/schemas/BlogPreviewDto"
                  }
                }
              },
              "text/json": {
                "schema": {
                  "type": "array",
                  "items": {
                    "$ref": "#/components/schemas/BlogPreviewDto"
                  }
                }
              }
            }
          }
        }
      }
    },
    "/api/Health": {
      "get": {
        "tags": [
          "Health"
        ],
        "operationId": "HealthCheck",
        "responses": {
          "200": {
            "description": "OK"
          }
        }
      }
    },
    "/api/Users": {
      "get": {
        "tags": [
          "Users"
        ],
        "parameters": [
          {
            "name": "Id",
            "in": "query",
            "schema": {
              "type": "integer",
              "format": "int32"
            }
          }
        ],
        "responses": {
          "200": {
            "description": "OK",
            "content": {
              "text/plain": {
                "schema": {
                  "$ref": "#/components/schemas/UserDto"
                }
              },
              "application/json": {
                "schema": {
                  "$ref": "#/components/schemas/UserDto"
                }
              },
              "text/json": {
                "schema": {
                  "$ref": "#/components/schemas/UserDto"
                }
              }
            }
          }
        }
      },
      "post": {
        "tags": [
          "Users"
        ],
        "requestBody": {
          "content": {
            "application/json": {
              "schema": {
                "$ref": "#/components/schemas/CreateUserCommand"
              }
            },
            "text/json": {
              "schema": {
                "$ref": "#/components/schemas/CreateUserCommand"
              }
            },
            "application/*+json": {
              "schema": {
                "$ref": "#/components/schemas/CreateUserCommand"
              }
            }
          }
        },
        "responses": {
          "200": {
            "description": "OK",
            "content": {
              "text/plain": {
                "schema": {
                  "$ref": "#/components/schemas/UserDto"
                }
              },
              "application/json": {
                "schema": {
                  "$ref": "#/components/schemas/UserDto"
                }
              },
              "text/json": {
                "schema": {
                  "$ref": "#/components/schemas/UserDto"
                }
              }
            }
          }
        }
      }
    }
  },
  "components": {
    "schemas": {
      "BlogPreviewDto": {
        "type": "object",
        "properties": {
          "id": {
            "type": "string",
            "format": "uuid"
          },
          "title": {
            "type": "string",
            "nullable": true
          },
          "content": {
            "type": "string",
            "nullable": true
          },
          "image": {
            "type": "string",
            "nullable": true
          },
          "url": {
            "type": "string",
            "nullable": true
          },
          "publishedDate": {
            "type": "string",
            "format": "date-time"
          }
        },
        "additionalProperties": false
      },
      "CreateUserCommand": {
        "type": "object",
        "properties": {
          "name": {
            "type": "string",
            "nullable": true
          },
          "username": {
            "type": "string",
            "nullable": true
          },
          "email": {
            "type": "string",
            "nullable": true
          }
        },
        "additionalProperties": false
      },
      "UserDto": {
        "type": "object",
        "properties": {
          "id": {
            "type": "integer",
            "format": "int32",
            "nullable": true
          },
          "name": {
            "type": "string",
            "nullable": true
          },
          "username": {
            "type": "string",
            "nullable": true
          },
          "email": {
            "type": "string",
            "nullable": true
          }
        },
        "additionalProperties": false
      }
    }
  }
}